ctxctx/__init__.py
ctxctx/app.py
ctxctx/cache.py
ctxctx/cli.py
ctxctx/config.py
ctxctx/content.py
ctxctx/exceptions.py
ctxctx/ignore.py
ctxctx/logging_utils.py
ctxctx/output.py
ctxctx/resolver.py
ctxctx/search.py
ctxctx/tree.py
ctxctx-0.3.10.dist-info/LICENSE
ctxctx-0.3.10.dist-info/METADATA
ctxctx-0.3.10.dist-info/WHEEL
ctxctx-0.3.10.dist-info/entry_points.txt
ctxctx-0.3.10.dist-info/RECORD
