Metadata-Version: 2.3
Name: ctxctx
Version: 0.3.10
Summary: Intelligently select, format, and present relevant project files and directory structure as context for LLMs.
License: MIT
Keywords: llm,context,cli,code,directory,files
Author: Toomes Gud
Author-email: toomesgud@gmail.com
Requires-Python: >=3.10
Classifier: Programming Language :: Python :: 3
Classifier: License :: OSI Approved :: MIT License
Classifier: Operating System :: OS Independent
Classifier: Intended Audience :: Developers
Classifier: Topic :: Software Development :: Build Tools
Classifier: Topic :: Utilities
Classifier: Environment :: Console
Requires-Dist: PyYAML (>=6.0)
Requires-Dist: pathspec (>=0.12.1)
